chaostoolkit_opentracing-0.18.1.dist-info/METADATA
chaostoolkit_opentracing-0.18.1.dist-info/WHEEL
chaostoolkit_opentracing-0.18.1.dist-info/entry_points.txt
chaostoolkit_opentracing-0.18.1.dist-info/licenses/LICENSE
chaostracing/__init__.py
chaostracing/control.py
chaostracing/metrics.py
chaostracing/oltp.py
chaostoolkit_opentracing-0.18.1.dist-info/RECORD
