Metadata-Version: 2.1
Name: chaostoolkit-opentracing
Version: 0.18.1
Summary: Chaos Toolkit OpenTracing Extension
Author-Email: Chaos Toolkit <contact@chaostoolkit.org>, Sylvain Hellegouarch <sh@defuze.org>
License: Apache-2.0
Classifier: Development Status :: 5 - Production/Stable
Classifier: Intended Audience :: Developers
Classifier: License :: Freely Distributable
Classifier: License :: OSI Approved :: Apache Software License
Classifier: Operating System :: OS Independent
Classifier: Programming Language :: Python
Classifier: Programming Language :: Python :: 3
Classifier: Programming Language :: Python :: 3.9
Classifier: Programming Language :: Python :: 3.10
Classifier: Programming Language :: Python :: 3.11
Classifier: Programming Language :: Python :: 3.12
Classifier: Programming Language :: Python :: Implementation
Classifier: Programming Language :: Python :: Implementation :: CPython
Requires-Python: >=3.9
Requires-Dist: chaostoolkit-lib>=1.42.1
Requires-Dist: opentracing>=2.4.0
Requires-Dist: opentelemetry-api>=1.24.0
Requires-Dist: opentelemetry-sdk>=1.24.0
Requires-Dist: opentelemetry-semantic-conventions>=0.45b0
Requires-Dist: opentelemetry-exporter-otlp-proto-http>=1.24.0
Requires-Dist: opentelemetry-instrumentation-httpx>=0.45b0
Requires-Dist: opentelemetry-instrumentation-requests>=0.45b0
Requires-Dist: opentelemetry-instrumentation-botocore>=0.45b0
Requires-Dist: opentelemetry-exporter-gcp-trace>=1.6.0
Requires-Dist: opentelemetry-resourcedetector-gcp>=1.6.0a0
Requires-Dist: opentelemetry-propagator-gcp>=1.6.0
Requires-Dist: opentelemetry-exporter-prometheus>=0.45b0
Requires-Dist: opentelemetry-propagator-b3>=1.24.0
Requires-Dist: opentelemetry-sdk-extension-aws>=2.0.1
Requires-Dist: opentelemetry-propagator-aws-xray>=1.0.1
Requires-Dist: opentelemetry-instrumentation-urllib3>=0.45b0
